odoo10_addon_base_import_default_enable_tracking-10.0.1.0.0.99.dev5-py2.7-nspkg.pth
odoo/addons/base_import_default_enable_tracking/README.rst
odoo/addons/base_import_default_enable_tracking/__init__.py
odoo/addons/base_import_default_enable_tracking/__manifest__.py
odoo/addons/base_import_default_enable_tracking/i18n/base_import_default_enable_tracking.pot
odoo/addons/base_import_default_enable_tracking/i18n/es.po
odoo/addons/base_import_default_enable_tracking/i18n/hr.po
odoo/addons/base_import_default_enable_tracking/i18n/it.po
odoo/addons/base_import_default_enable_tracking/static/description/icon.png
odoo/addons/base_import_default_enable_tracking/static/src/xml/base_import.xml
odoo10_addon_base_import_default_enable_tracking-10.0.1.0.0.99.dev5.dist-info/DESCRIPTION.rst
odoo10_addon_base_import_default_enable_tracking-10.0.1.0.0.99.dev5.dist-info/METADATA
odoo10_addon_base_import_default_enable_tracking-10.0.1.0.0.99.dev5.dist-info/RECORD
odoo10_addon_base_import_default_enable_tracking-10.0.1.0.0.99.dev5.dist-info/WHEEL
odoo10_addon_base_import_default_enable_tracking-10.0.1.0.0.99.dev5.dist-info/metadata.json
odoo10_addon_base_import_default_enable_tracking-10.0.1.0.0.99.dev5.dist-info/namespace_packages.txt
odoo10_addon_base_import_default_enable_tracking-10.0.1.0.0.99.dev5.dist-info/top_level.txt
