Metadata-Version: 2.0
Name: odoo10-addon-base-import-default-enable-tracking
Version: 10.0.1.0.0.99.dev5
Summary: This modules simply enables history tracking when doing an import.
Home-page: https://www.acsone.eu
Author: ACSONE SA/NV, Odoo Community Association (OCA)
Author-email: support@odoo-community.org
License: AGPL-3
Platform: UNKNOWN
Classifier: Programming Language :: Python
Classifier: Framework :: Odoo
Classifier: License :: OSI Approved :: GNU Affero General Public License v3
Requires-Python: ~=2.7
Requires-Dist: odoo (<10.1dev,>=10.0)
